guid/__init__.py
guid/guid.py
guid-0.2.1.dist-info/LICENSE
guid-0.2.1.dist-info/WHEEL
guid-0.2.1.dist-info/METADATA
guid-0.2.1.dist-info/RECORD
