Metadata-Version: 2.1
Name: guid
Version: 0.2.1
Summary: Human friendly GUID/UUID library
Author: Logi Leifsson
Author-email: logileifs@gmail.com
Requires-Python: >=3.4,<4.0
Classifier: Programming Language :: Python :: 3
Classifier: Programming Language :: Python :: 3.4
Classifier: Programming Language :: Python :: 3.5
Classifier: Programming Language :: Python :: 3.6
Classifier: Programming Language :: Python :: 3.7
Classifier: Programming Language :: Python :: 3.8
Classifier: Programming Language :: Python :: 3.9
